mailing_manager/__init__.py
mailing_manager/admin.py
mailing_manager/apps.py
mailing_manager/forms.py
mailing_manager/mail_handler.py
mailing_manager/mail_queue_handler.py
mailing_manager/mail_template.py
mailing_manager/migrations/0001_initial.py
mailing_manager/migrations/0002_auto_20201211_1428.py
mailing_manager/migrations/0003_alter_mail_id.py
mailing_manager/migrations/0004_auto_20210422_1407.py
mailing_manager/migrations/__init__.py
mailing_manager/models.py
mailing_manager/templates/admin/templatemail_preview.html
mailing_manager/templates/tests/mail.html
mailing_manager/views.py
mailing_manager-0.1.1.dist-info/LICENSE
mailing_manager-0.1.1.dist-info/WHEEL
mailing_manager-0.1.1.dist-info/METADATA
mailing_manager-0.1.1.dist-info/RECORD
