Metadata-Version: 2.1
Name: mailing-manager
Version: 0.1.1
Summary: Basic mail template managing integrated with admin panel and django-mail-queue.
License: BSD
Author: Codi Cooperatiu
Author-email: hola@codi.coop
Requires-Python: >=3.6,<4.0
Classifier: License :: Other/Proprietary License
Classifier: Programming Language :: Python :: 3
Classifier: Programming Language :: Python :: 3.10
Classifier: Programming Language :: Python :: 3.6
Classifier: Programming Language :: Python :: 3.7
Classifier: Programming Language :: Python :: 3.8
Classifier: Programming Language :: Python :: 3.9
Requires-Dist: Django (>=3.2.4,<4.0.0)
Requires-Dist: django-mail-queue (>=3.2.4,<4.0.0)
